{
  "openapi": "3.0.4",
  "info": {
    "title": "Backend",
    "version": "1.0"
  },
  "paths": {
    "/api/Customers": {
      "get": {
        "tags": [
          "Customers"
        ],
        "parameters": [
          {
            "name": "includeInactive",
            "in": "query",
            "schema": {
              "type": "boolean",
              "default": false
            }
          }
        ],
        "responses": {
          "200": {
            "description": "OK",
            "content": {
              "application/json": {
                "schema": {
                  "$ref": "#/components/schemas/CustomerListApiResponse"
                }
              }
            }
          }
        }
      },
      "post": {
        "tags": [
          "Customers"
        ],
        "requestBody": {
          "content": {
            "application/json": {
              "schema": {
                "$ref": "#/components/schemas/CustomerDto"
              }
            },
            "text/json": {
              "schema": {
                "$ref": "#/components/schemas/CustomerDto"
              }
            },
            "application/*+json": {
              "schema": {
                "$ref": "#/components/schemas/CustomerDto"
              }
            }
          }
        },
        "responses": {
          "201": {
            "description": "Created",
            "content": {
              "application/json": {
                "schema": {
                  "$ref": "#/components/schemas/CustomerApiResponse"
                }
              }
            }
          },
          "400": {
            "description": "Bad Request",
            "content": {
              "application/json": {
                "schema": {
                  "$ref": "#/components/schemas/CustomerApiResponse"
                }
              }
            }
          }
        }
      }
    },
    "/api/Customers/paginated": {
      "get": {
        "tags": [
          "Customers"
        ],
        "parameters": [
          {
            "name": "pageNumber",
            "in": "query",
            "schema": {
              "type": "integer",
              "format": "int32",
              "default": 1
            }
          },
          {
            "name": "pageSize",
            "in": "query",
            "schema": {
              "type": "integer",
              "format": "int32",
              "default": 10
            }
          },
          {
            "name": "includeInactive",
            "in": "query",
            "schema": {
              "type": "boolean",
              "default": false
            }
          }
        ],
        "responses": {
          "200": {
            "description": "OK",
            "content": {
              "application/json": {
                "schema": {
                  "$ref": "#/components/schemas/CustomerPaginatedResponse"
                }
              }
            }
          }
        }
      }
    },
    "/api/Customers/{id}": {
      "get": {
        "tags": [
          "Customers"
        ],
        "parameters": [
          {
            "name": "id",
            "in": "path",
            "required": true,
            "schema": {
              "type": "integer",
              "format": "int32"
            }
          }
        ],
        "responses": {
          "200": {
            "description": "OK",
            "content": {
              "application/json": {
                "schema": {
                  "$ref": "#/components/schemas/CustomerApiResponse"
                }
              }
            }
          },
          "404": {
            "description": "Not Found",
            "content": {
              "application/json": {
                "schema": {
                  "$ref": "#/components/schemas/CustomerApiResponse"
                }
              }
            }
          }
        }
      },
      "put": {
        "tags": [
          "Customers"
        ],
        "parameters": [
          {
            "name": "id",
            "in": "path",
            "required": true,
            "schema": {
              "type": "integer",
              "format": "int32"
            }
          }
        ],
        "requestBody": {
          "content": {
            "application/json": {
              "schema": {
                "$ref": "#/components/schemas/CustomerUpdateDto"
              }
            },
            "text/json": {
              "schema": {
                "$ref": "#/components/schemas/CustomerUpdateDto"
              }
            },
            "application/*+json": {
              "schema": {
                "$ref": "#/components/schemas/CustomerUpdateDto"
              }
            }
          }
        },
        "responses": {
          "200": {
            "description": "OK",
            "content": {
              "application/json": {
                "schema": {
                  "$ref": "#/components/schemas/BooleanApiResponse"
                }
              }
            }
          },
          "404": {
            "description": "Not Found",
            "content": {
              "application/json": {
                "schema": {
                  "$ref": "#/components/schemas/BooleanApiResponse"
                }
              }
            }
          },
          "400": {
            "description": "Bad Request",
            "content": {
              "application/json": {
                "schema": {
                  "$ref": "#/components/schemas/BooleanApiResponse"
                }
              }
            }
          }
        }
      },
      "delete": {
        "tags": [
          "Customers"
        ],
        "parameters": [
          {
            "name": "id",
            "in": "path",
            "required": true,
            "schema": {
              "type": "integer",
              "format": "int32"
            }
          }
        ],
        "responses": {
          "200": {
            "description": "OK",
            "content": {
              "application/json": {
                "schema": {
                  "$ref": "#/components/schemas/BooleanApiResponse"
                }
              }
            }
          },
          "404": {
            "description": "Not Found",
            "content": {
              "application/json": {
                "schema": {
                  "$ref": "#/components/schemas/BooleanApiResponse"
                }
              }
            }
          }
        }
      }
    },
    "/api/Customers/{id}/restore": {
      "post": {
        "tags": [
          "Customers"
        ],
        "parameters": [
          {
            "name": "id",
            "in": "path",
            "required": true,
            "schema": {
              "type": "integer",
              "format": "int32"
            }
          }
        ],
        "responses": {
          "200": {
            "description": "OK",
            "content": {
              "application/json": {
                "schema": {
                  "$ref": "#/components/schemas/BooleanApiResponse"
                }
              }
            }
          },
          "404": {
            "description": "Not Found",
            "content": {
              "application/json": {
                "schema": {
                  "$ref": "#/components/schemas/BooleanApiResponse"
                }
              }
            }
          }
        }
      }
    },
    "/api/Customers/search": {
      "get": {
        "tags": [
          "Customers"
        ],
        "parameters": [
          {
            "name": "term",
            "in": "query",
            "schema": {
              "type": "string"
            }
          },
          {
            "name": "includeInactive",
            "in": "query",
            "schema": {
              "type": "boolean",
              "default": false
            }
          }
        ],
        "responses": {
          "200": {
            "description": "OK",
            "content": {
              "application/json": {
                "schema": {
                  "$ref": "#/components/schemas/CustomerListApiResponse"
                }
              }
            }
          }
        }
      }
    },
    "/api/Customers/{id}/balance": {
      "get": {
        "tags": [
          "Customers"
        ],
        "parameters": [
          {
            "name": "id",
            "in": "path",
            "required": true,
            "schema": {
              "type": "integer",
              "format": "int32"
            }
          }
        ],
        "responses": {
          "200": {
            "description": "OK",
            "content": {
              "application/json": {
                "schema": {
                  "$ref": "#/components/schemas/DecimalApiResponse"
                }
              }
            }
          }
        }
      },
      "patch": {
        "tags": [
          "Customers"
        ],
        "parameters": [
          {
            "name": "id",
            "in": "path",
            "required": true,
            "schema": {
              "type": "integer",
              "format": "int32"
            }
          }
        ],
        "requestBody": {
          "content": {
            "application/json": {
              "schema": {
                "type": "number",
                "format": "double"
              }
            },
            "text/json": {
              "schema": {
                "type": "number",
                "format": "double"
              }
            },
            "application/*+json": {
              "schema": {
                "type": "number",
                "format": "double"
              }
            }
          }
        },
        "responses": {
          "200": {
            "description": "OK",
            "content": {
              "application/json": {
                "schema": {
                  "$ref": "#/components/schemas/BooleanApiResponse"
                }
              }
            }
          }
        }
      }
    },
    "/api/Suppliers": {
      "get": {
        "tags": [
          "Suppliers"
        ],
        "parameters": [
          {
            "name": "includeInactive",
            "in": "query",
            "schema": {
              "type": "boolean",
              "default": false
            }
          }
        ],
        "responses": {
          "200": {
            "description": "OK",
            "content": {
              "application/json": {
                "schema": {
                  "$ref": "#/components/schemas/SupplierListApiResponse"
                }
              }
            }
          }
        }
      },
      "post": {
        "tags": [
          "Suppliers"
        ],
        "requestBody": {
          "content": {
            "application/json": {
              "schema": {
                "$ref": "#/components/schemas/SupplierDto"
              }
            },
            "text/json": {
              "schema": {
                "$ref": "#/components/schemas/SupplierDto"
              }
            },
            "application/*+json": {
              "schema": {
                "$ref": "#/components/schemas/SupplierDto"
              }
            }
          }
        },
        "responses": {
          "201": {
            "description": "Created",
            "content": {
              "application/json": {
                "schema": {
                  "$ref": "#/components/schemas/SupplierApiResponse"
                }
              }
            }
          },
          "400": {
            "description": "Bad Request",
            "content": {
              "application/json": {
                "schema": {
                  "$ref": "#/components/schemas/SupplierApiResponse"
                }
              }
            }
          }
        }
      }
    },
    "/api/Suppliers/paginated": {
      "get": {
        "tags": [
          "Suppliers"
        ],
        "parameters": [
          {
            "name": "pageNumber",
            "in": "query",
            "schema": {
              "type": "integer",
              "format": "int32",
              "default": 1
            }
          },
          {
            "name": "pageSize",
            "in": "query",
            "schema": {
              "type": "integer",
              "format": "int32",
              "default": 10
            }
          },
          {
            "name": "includeInactive",
            "in": "query",
            "schema": {
              "type": "boolean",
              "default": false
            }
          }
        ],
        "responses": {
          "200": {
            "description": "OK",
            "content": {
              "application/json": {
                "schema": {
                  "$ref": "#/components/schemas/SupplierPaginatedResponse"
                }
              }
            }
          }
        }
      }
    },
    "/api/Suppliers/{id}": {
      "get": {
        "tags": [
          "Suppliers"
        ],
        "parameters": [
          {
            "name": "id",
            "in": "path",
            "required": true,
            "schema": {
              "type": "integer",
              "format": "int32"
            }
          }
        ],
        "responses": {
          "200": {
            "description": "OK",
            "content": {
              "application/json": {
                "schema": {
                  "$ref": "#/components/schemas/SupplierApiResponse"
                }
              }
            }
          },
          "404": {
            "description": "Not Found",
            "content": {
              "application/json": {
                "schema": {
                  "$ref": "#/components/schemas/SupplierApiResponse"
                }
              }
            }
          }
        }
      },
      "put": {
        "tags": [
          "Suppliers"
        ],
        "parameters": [
          {
            "name": "id",
            "in": "path",
            "required": true,
            "schema": {
              "type": "integer",
              "format": "int32"
            }
          }
        ],
        "requestBody": {
          "content": {
            "application/json": {
              "schema": {
                "$ref": "#/components/schemas/SupplierUpdateDto"
              }
            },
            "text/json": {
              "schema": {
                "$ref": "#/components/schemas/SupplierUpdateDto"
              }
            },
            "application/*+json": {
              "schema": {
                "$ref": "#/components/schemas/SupplierUpdateDto"
              }
            }
          }
        },
        "responses": {
          "200": {
            "description": "OK",
            "content": {
              "application/json": {
                "schema": {
                  "$ref": "#/components/schemas/BooleanApiResponse"
                }
              }
            }
          },
          "404": {
            "description": "Not Found",
            "content": {
              "application/json": {
                "schema": {
                  "$ref": "#/components/schemas/BooleanApiResponse"
                }
              }
            }
          },
          "400": {
            "description": "Bad Request",
            "content": {
              "application/json": {
                "schema": {
                  "$ref": "#/components/schemas/BooleanApiResponse"
                }
              }
            }
          }
        }
      },
      "delete": {
        "tags": [
          "Suppliers"
        ],
        "parameters": [
          {
            "name": "id",
            "in": "path",
            "required": true,
            "schema": {
              "type": "integer",
              "format": "int32"
            }
          }
        ],
        "responses": {
          "200": {
            "description": "OK",
            "content": {
              "application/json": {
                "schema": {
                  "$ref": "#/components/schemas/BooleanApiResponse"
                }
              }
            }
          },
          "404": {
            "description": "Not Found",
            "content": {
              "application/json": {
                "schema": {
                  "$ref": "#/components/schemas/BooleanApiResponse"
                }
              }
            }
          }
        }
      }
    },
    "/api/Suppliers/{id}/restore": {
      "post": {
        "tags": [
          "Suppliers"
        ],
        "parameters": [
          {
            "name": "id",
            "in": "path",
            "required": true,
            "schema": {
              "type": "integer",
              "format": "int32"
            }
          }
        ],
        "responses": {
          "200": {
            "description": "OK",
            "content": {
              "application/json": {
                "schema": {
                  "$ref": "#/components/schemas/BooleanApiResponse"
                }
              }
            }
          },
          "404": {
            "description": "Not Found",
            "content": {
              "application/json": {
                "schema": {
                  "$ref": "#/components/schemas/BooleanApiResponse"
                }
              }
            }
          }
        }
      }
    },
    "/api/Suppliers/search": {
      "get": {
        "tags": [
          "Suppliers"
        ],
        "parameters": [
          {
            "name": "term",
            "in": "query",
            "schema": {
              "type": "string"
            }
          },
          {
            "name": "includeInactive",
            "in": "query",
            "schema": {
              "type": "boolean",
              "default": false
            }
          }
        ],
        "responses": {
          "200": {
            "description": "OK",
            "content": {
              "application/json": {
                "schema": {
                  "$ref": "#/components/schemas/SupplierListApiResponse"
                }
              }
            }
          }
        }
      }
    },
    "/api/Suppliers/{id}/balance": {
      "get": {
        "tags": [
          "Suppliers"
        ],
        "parameters": [
          {
            "name": "id",
            "in": "path",
            "required": true,
            "schema": {
              "type": "integer",
              "format": "int32"
            }
          }
        ],
        "responses": {
          "200": {
            "description": "OK",
            "content": {
              "application/json": {
                "schema": {
                  "$ref": "#/components/schemas/DecimalApiResponse"
                }
              }
            }
          }
        }
      },
      "patch": {
        "tags": [
          "Suppliers"
        ],
        "parameters": [
          {
            "name": "id",
            "in": "path",
            "required": true,
            "schema": {
              "type": "integer",
              "format": "int32"
            }
          }
        ],
        "requestBody": {
          "content": {
            "application/json": {
              "schema": {
                "type": "number",
                "format": "double"
              }
            },
            "text/json": {
              "schema": {
                "type": "number",
                "format": "double"
              }
            },
            "application/*+json": {
              "schema": {
                "type": "number",
                "format": "double"
              }
            }
          }
        },
        "responses": {
          "200": {
            "description": "OK",
            "content": {
              "application/json": {
                "schema": {
                  "$ref": "#/components/schemas/BooleanApiResponse"
                }
              }
            }
          }
        }
      }
    },
    "/api/Suppliers/with-balance": {
      "get": {
        "tags": [
          "Suppliers"
        ],
        "responses": {
          "200": {
            "description": "OK",
            "content": {
              "application/json": {
                "schema": {
                  "$ref": "#/components/schemas/SupplierListApiResponse"
                }
              }
            }
          }
        }
      }
    },
    "/api/Users/login": {
      "post": {
        "tags": [
          "Users"
        ],
        "requestBody": {
          "content": {
            "application/json": {
              "schema": {
                "$ref": "#/components/schemas/LoginDto"
              }
            },
            "text/json": {
              "schema": {
                "$ref": "#/components/schemas/LoginDto"
              }
            },
            "application/*+json": {
              "schema": {
                "$ref": "#/components/schemas/LoginDto"
              }
            }
          }
        },
        "responses": {
          "200": {
            "description": "OK",
            "content": {
              "application/json": {
                "schema": {
                  "$ref": "#/components/schemas/UserLoginResponseApiResponse"
                }
              }
            }
          },
          "401": {
            "description": "Unauthorized",
            "content": {
              "application/json": {
                "schema": {
                  "$ref": "#/components/schemas/ObjectApiResponse"
                }
              }
            }
          }
        }
      }
    },
    "/api/Users": {
      "get": {
        "tags": [
          "Users"
        ],
        "parameters": [
          {
            "name": "includeInactive",
            "in": "query",
            "schema": {
              "type": "boolean",
              "default": false
            }
          }
        ],
        "responses": {
          "200": {
            "description": "OK",
            "content": {
              "application/json": {
                "schema": {
                  "$ref": "#/components/schemas/UserListApiResponse"
                }
              }
            }
          }
        }
      },
      "post": {
        "tags": [
          "Users"
        ],
        "requestBody": {
          "content": {
            "application/json": {
              "schema": {
                "$ref": "#/components/schemas/CreateUserDto"
              }
            },
            "text/json": {
              "schema": {
                "$ref": "#/components/schemas/CreateUserDto"
              }
            },
            "application/*+json": {
              "schema": {
                "$ref": "#/components/schemas/CreateUserDto"
              }
            }
          }
        },
        "responses": {
          "201": {
            "description": "Created",
            "content": {
              "application/json": {
                "schema": {
                  "$ref": "#/components/schemas/UserApiResponse"
                }
              }
            }
          },
          "400": {
            "description": "Bad Request",
            "content": {
              "application/json": {
                "schema": {
                  "$ref": "#/components/schemas/UserApiResponse"
                }
              }
            }
          }
        }
      }
    },
    "/api/Users/paginated": {
      "get": {
        "tags": [
          "Users"
        ],
        "parameters": [
          {
            "name": "pageNumber",
            "in": "query",
            "schema": {
              "type": "integer",
              "format": "int32",
              "default": 1
            }
          },
          {
            "name": "pageSize",
            "in": "query",
            "schema": {
              "type": "integer",
              "format": "int32",
              "default": 10
            }
          },
          {
            "name": "includeInactive",
            "in": "query",
            "schema": {
              "type": "boolean",
              "default": false
            }
          }
        ],
        "responses": {
          "200": {
            "description": "OK",
            "content": {
              "application/json": {
                "schema": {
                  "$ref": "#/components/schemas/UserPaginatedResponse"
                }
              }
            }
          }
        }
      }
    },
    "/api/Users/{id}": {
      "get": {
        "tags": [
          "Users"
        ],
        "parameters": [
          {
            "name": "id",
            "in": "path",
            "required": true,
            "schema": {
              "type": "integer",
              "format": "int32"
            }
          }
        ],
        "responses": {
          "200": {
            "description": "OK",
            "content": {
              "application/json": {
                "schema": {
                  "$ref": "#/components/schemas/UserApiResponse"
                }
              }
            }
          },
          "404": {
            "description": "Not Found",
            "content": {
              "application/json": {
                "schema": {
                  "$ref": "#/components/schemas/UserApiResponse"
                }
              }
            }
          }
        }
      },
      "put": {
        "tags": [
          "Users"
        ],
        "parameters": [
          {
            "name": "id",
            "in": "path",
            "required": true,
            "schema": {
              "type": "integer",
              "format": "int32"
            }
          }
        ],
        "requestBody": {
          "content": {
            "application/json": {
              "schema": {
                "$ref": "#/components/schemas/UpdateUserDto"
              }
            },
            "text/json": {
              "schema": {
                "$ref": "#/components/schemas/UpdateUserDto"
              }
            },
            "application/*+json": {
              "schema": {
                "$ref": "#/components/schemas/UpdateUserDto"
              }
            }
          }
        },
        "responses": {
          "200": {
            "description": "OK",
            "content": {
              "application/json": {
                "schema": {
                  "$ref": "#/components/schemas/BooleanApiResponse"
                }
              }
            }
          },
          "404": {
            "description": "Not Found",
            "content": {
              "application/json": {
                "schema": {
                  "$ref": "#/components/schemas/BooleanApiResponse"
                }
              }
            }
          },
          "400": {
            "description": "Bad Request",
            "content": {
              "application/json": {
                "schema": {
                  "$ref": "#/components/schemas/BooleanApiResponse"
                }
              }
            }
          }
        }
      },
      "delete": {
        "tags": [
          "Users"
        ],
        "parameters": [
          {
            "name": "id",
            "in": "path",
            "required": true,
            "schema": {
              "type": "integer",
              "format": "int32"
            }
          }
        ],
        "responses": {
          "200": {
            "description": "OK",
            "content": {
              "application/json": {
                "schema": {
                  "$ref": "#/components/schemas/BooleanApiResponse"
                }
              }
            }
          },
          "404": {
            "description": "Not Found",
            "content": {
              "application/json": {
                "schema": {
                  "$ref": "#/components/schemas/BooleanApiResponse"
                }
              }
            }
          }
        }
      }
    },
    "/api/Users/profile": {
      "get": {
        "tags": [
          "Users"
        ],
        "responses": {
          "200": {
            "description": "OK",
            "content": {
              "application/json": {
                "schema": {
                  "$ref": "#/components/schemas/UserApiResponse"
                }
              }
            }
          }
        }
      }
    },
    "/api/Users/{id}/restore": {
      "post": {
        "tags": [
          "Users"
        ],
        "parameters": [
          {
            "name": "id",
            "in": "path",
            "required": true,
            "schema": {
              "type": "integer",
              "format": "int32"
            }
          }
        ],
        "responses": {
          "200": {
            "description": "OK",
            "content": {
              "application/json": {
                "schema": {
                  "$ref": "#/components/schemas/BooleanApiResponse"
                }
              }
            }
          },
          "404": {
            "description": "Not Found",
            "content": {
              "application/json": {
                "schema": {
                  "$ref": "#/components/schemas/BooleanApiResponse"
                }
              }
            }
          }
        }
      }
    },
    "/api/Users/change-password": {
      "post": {
        "tags": [
          "Users"
        ],
        "requestBody": {
          "content": {
            "application/json": {
              "schema": {
                "$ref": "#/components/schemas/ChangePasswordDto"
              }
            },
            "text/json": {
              "schema": {
                "$ref": "#/components/schemas/ChangePasswordDto"
              }
            },
            "application/*+json": {
              "schema": {
                "$ref": "#/components/schemas/ChangePasswordDto"
              }
            }
          }
        },
        "responses": {
          "200": {
            "description": "OK",
            "content": {
              "application/json": {
                "schema": {
                  "$ref": "#/components/schemas/BooleanApiResponse"
                }
              }
            }
          },
          "400": {
            "description": "Bad Request",
            "content": {
              "application/json": {
                "schema": {
                  "$ref": "#/components/schemas/BooleanApiResponse"
                }
              }
            }
          }
        }
      }
    },
    "/api/Users/search": {
      "get": {
        "tags": [
          "Users"
        ],
        "parameters": [
          {
            "name": "term",
            "in": "query",
            "schema": {
              "type": "string"
            }
          },
          {
            "name": "includeInactive",
            "in": "query",
            "schema": {
              "type": "boolean",
              "default": false
            }
          }
        ],
        "responses": {
          "200": {
            "description": "OK",
            "content": {
              "application/json": {
                "schema": {
                  "$ref": "#/components/schemas/UserListApiResponse"
                }
              }
            }
          }
        }
      }
    },
    "/api/Users/role/{role}": {
      "get": {
        "tags": [
          "Users"
        ],
        "parameters": [
          {
            "name": "role",
            "in": "path",
            "required": true,
            "schema": {
              "type": "string"
            }
          }
        ],
        "responses": {
          "200": {
            "description": "OK",
            "content": {
              "application/json": {
                "schema": {
                  "$ref": "#/components/schemas/UserListApiResponse"
                }
              }
            }
          }
        }
      }
    },
    "/api/Users/{id}/status": {
      "patch": {
        "tags": [
          "Users"
        ],
        "parameters": [
          {
            "name": "id",
            "in": "path",
            "required": true,
            "schema": {
              "type": "integer",
              "format": "int32"
            }
          }
        ],
        "requestBody": {
          "content": {
            "application/json": {
              "schema": {
                "$ref": "#/components/schemas/UpdateUserStatusDto"
              }
            },
            "text/json": {
              "schema": {
                "$ref": "#/components/schemas/UpdateUserStatusDto"
              }
            },
            "application/*+json": {
              "schema": {
                "$ref": "#/components/schemas/UpdateUserStatusDto"
              }
            }
          }
        },
        "responses": {
          "200": {
            "description": "OK",
            "content": {
              "application/json": {
                "schema": {
                  "$ref": "#/components/schemas/BooleanApiResponse"
                }
              }
            }
          },
          "404": {
            "description": "Not Found",
            "content": {
              "application/json": {
                "schema": {
                  "$ref": "#/components/schemas/BooleanApiResponse"
                }
              }
            }
          }
        }
      }
    }
  },
  "components": {
    "schemas": {
      "BooleanApiResponse": {
        "type": "object",
        "properties": {
          "success": {
            "type": "boolean"
          },
          "message": {
            "type": "string",
            "nullable": true
          },
          "data": {
            "type": "boolean"
          },
          "errors": {
            "type": "array",
            "items": {
              "type": "string"
            },
            "nullable": true
          },
          "timestamp": {
            "type": "string",
            "format": "date-time"
          }
        },
        "additionalProperties": false
      },
      "ChangePasswordDto": {
        "required": [
          "confirmPassword",
          "currentPassword",
          "newPassword"
        ],
        "type": "object",
        "properties": {
          "currentPassword": {
            "minLength": 1,
            "type": "string"
          },
          "newPassword": {
            "maxLength": 100,
            "minLength": 6,
            "pattern": "^(?=.*[a-z])(?=.*[A-Z])(?=.*\\d).+$",
            "type": "string"
          },
          "confirmPassword": {
            "minLength": 1,
            "type": "string"
          }
        },
        "additionalProperties": false
      },
      "CreateUserDto": {
        "required": [
          "name",
          "password",
          "role",
          "username"
        ],
        "type": "object",
        "properties": {
          "name": {
            "maxLength": 100,
            "minLength": 2,
            "type": "string"
          },
          "email": {
            "maxLength": 100,
            "minLength": 0,
            "type": "string",
            "format": "email",
            "nullable": true
          },
          "phone": {
            "maxLength": 15,
            "minLength": 0,
            "type": "string",
            "format": "tel",
            "nullable": true
          },
          "address": {
            "maxLength": 500,
            "minLength": 0,
            "type": "string",
            "nullable": true
          },
          "username": {
            "maxLength": 50,
            "minLength": 3,
            "pattern": "^[a-zA-Z0-9_]+$",
            "type": "string"
          },
          "password": {
            "maxLength": 100,
            "minLength": 6,
            "pattern": "^(?=.*[a-z])(?=.*[A-Z])(?=.*\\d).+$",
            "type": "string"
          },
          "role": {
            "minLength": 1,
            "pattern": "^(admin|manager|staff)$",
            "type": "string"
          },
          "notes": {
            "maxLength": 1000,
            "minLength": 0,
            "type": "string",
            "nullable": true
          }
        },
        "additionalProperties": false
      },
      "Customer": {
        "type": "object",
        "properties": {
          "customerId": {
            "type": "integer",
            "format": "int32"
          },
          "fullName": {
            "type": "string",
            "nullable": true
          },
          "phone": {
            "type": "string",
            "nullable": true
          },
          "address": {
            "type": "string",
            "nullable": true
          },
          "currentBalance": {
            "type": "number",
            "format": "double"
          },
          "customerType": {
            "type": "string",
            "nullable": true
          },
          "isActive": {
            "type": "boolean"
          },
          "createdAt": {
            "type": "string",
            "format": "date-time"
          },
          "updatedAt": {
            "type": "string",
            "format": "date-time"
          },
          "notes": {
            "type": "string",
            "nullable": true
          }
        },
        "additionalProperties": false
      },
      "CustomerApiResponse": {
        "type": "object",
        "properties": {
          "success": {
            "type": "boolean"
          },
          "message": {
            "type": "string",
            "nullable": true
          },
          "data": {
            "$ref": "#/components/schemas/Customer"
          },
          "errors": {
            "type": "array",
            "items": {
              "type": "string"
            },
            "nullable": true
          },
          "timestamp": {
            "type": "string",
            "format": "date-time"
          }
        },
        "additionalProperties": false
      },
      "CustomerDto": {
        "required": [
          "customerType",
          "fullName"
        ],
        "type": "object",
        "properties": {
          "fullName": {
            "maxLength": 100,
            "minLength": 2,
            "type": "string"
          },
          "phone": {
            "maxLength": 15,
            "minLength": 0,
            "type": "string",
            "format": "tel",
            "nullable": true
          },
          "address": {
            "maxLength": 500,
            "minLength": 0,
            "type": "string",
            "nullable": true
          },
          "customerType": {
            "minLength": 1,
            "pattern": "^(regular|wholesale|retail|contractor|walkin)$",
            "type": "string"
          },
          "notes": {
            "maxLength": 1000,
            "minLength": 0,
            "type": "string",
            "nullable": true
          }
        },
        "additionalProperties": false
      },
      "CustomerListApiResponse": {
        "type": "object",
        "properties": {
          "success": {
            "type": "boolean"
          },
          "message": {
            "type": "string",
            "nullable": true
          },
          "data": {
            "type": "array",
            "items": {
              "$ref": "#/components/schemas/Customer"
            },
            "nullable": true
          },
          "errors": {
            "type": "array",
            "items": {
              "type": "string"
            },
            "nullable": true
          },
          "timestamp": {
            "type": "string",
            "format": "date-time"
          }
        },
        "additionalProperties": false
      },
      "CustomerPaginatedResponse": {
        "type": "object",
        "properties": {
          "success": {
            "type": "boolean"
          },
          "message": {
            "type": "string",
            "nullable": true
          },
          "data": {
            "type": "array",
            "items": {
              "$ref": "#/components/schemas/Customer"
            },
            "nullable": true
          },
          "totalRecords": {
            "type": "integer",
            "format": "int32"
          },
          "pageNumber": {
            "type": "integer",
            "format": "int32"
          },
          "pageSize": {
            "type": "integer",
            "format": "int32"
          },
          "totalPages": {
            "type": "integer",
            "format": "int32",
            "readOnly": true
          }
        },
        "additionalProperties": false
      },
      "CustomerUpdateDto": {
        "required": [
          "customerType",
          "fullName"
        ],
        "type": "object",
        "properties": {
          "fullName": {
            "maxLength": 100,
            "minLength": 2,
            "type": "string"
          },
          "phone": {
            "maxLength": 15,
            "minLength": 0,
            "type": "string",
            "format": "tel",
            "nullable": true
          },
          "address": {
            "maxLength": 500,
            "minLength": 0,
            "type": "string",
            "nullable": true
          },
          "customerType": {
            "minLength": 1,
            "pattern": "^(regular|wholesale|retail|contractor|walkin)$",
            "type": "string"
          },
          "notes": {
            "maxLength": 1000,
            "minLength": 0,
            "type": "string",
            "nullable": true
          }
        },
        "additionalProperties": false
      },
      "DecimalApiResponse": {
        "type": "object",
        "properties": {
          "success": {
            "type": "boolean"
          },
          "message": {
            "type": "string",
            "nullable": true
          },
          "data": {
            "type": "number",
            "format": "double"
          },
          "errors": {
            "type": "array",
            "items": {
              "type": "string"
            },
            "nullable": true
          },
          "timestamp": {
            "type": "string",
            "format": "date-time"
          }
        },
        "additionalProperties": false
      },
      "LoginDto": {
        "required": [
          "password",
          "username"
        ],
        "type": "object",
        "properties": {
          "username": {
            "minLength": 1,
            "type": "string"
          },
          "password": {
            "minLength": 1,
            "type": "string"
          }
        },
        "additionalProperties": false
      },
      "ObjectApiResponse": {
        "type": "object",
        "properties": {
          "success": {
            "type": "boolean"
          },
          "message": {
            "type": "string",
            "nullable": true
          },
          "data": {
            "nullable": true
          },
          "errors": {
            "type": "array",
            "items": {
              "type": "string"
            },
            "nullable": true
          },
          "timestamp": {
            "type": "string",
            "format": "date-time"
          }
        },
        "additionalProperties": false
      },
      "Supplier": {
        "type": "object",
        "properties": {
          "supplierId": {
            "type": "integer",
            "format": "int32"
          },
          "name": {
            "type": "string",
            "nullable": true
          },
          "contact": {
            "type": "string",
            "nullable": true
          },
          "address": {
            "type": "string",
            "nullable": true
          },
          "accountBalance": {
            "type": "number",
            "format": "double"
          },
          "isActive": {
            "type": "boolean"
          },
          "createdAt": {
            "type": "string",
            "format": "date-time"
          },
          "updatedAt": {
            "type": "string",
            "format": "date-time"
          },
          "notes": {
            "type": "string",
            "nullable": true
          }
        },
        "additionalProperties": false
      },
      "SupplierApiResponse": {
        "type": "object",
        "properties": {
          "success": {
            "type": "boolean"
          },
          "message": {
            "type": "string",
            "nullable": true
          },
          "data": {
            "$ref": "#/components/schemas/Supplier"
          },
          "errors": {
            "type": "array",
            "items": {
              "type": "string"
            },
            "nullable": true
          },
          "timestamp": {
            "type": "string",
            "format": "date-time"
          }
        },
        "additionalProperties": false
      },
      "SupplierDto": {
        "required": [
          "name"
        ],
        "type": "object",
        "properties": {
          "name": {
            "maxLength": 100,
            "minLength": 2,
            "type": "string"
          },
          "contact": {
            "maxLength": 15,
            "minLength": 0,
            "type": "string",
            "format": "tel",
            "nullable": true
          },
          "address": {
            "maxLength": 500,
            "minLength": 0,
            "type": "string",
            "nullable": true
          },
          "notes": {
            "maxLength": 1000,
            "minLength": 0,
            "type": "string",
            "nullable": true
          }
        },
        "additionalProperties": false
      },
      "SupplierListApiResponse": {
        "type": "object",
        "properties": {
          "success": {
            "type": "boolean"
          },
          "message": {
            "type": "string",
            "nullable": true
          },
          "data": {
            "type": "array",
            "items": {
              "$ref": "#/components/schemas/Supplier"
            },
            "nullable": true
          },
          "errors": {
            "type": "array",
            "items": {
              "type": "string"
            },
            "nullable": true
          },
          "timestamp": {
            "type": "string",
            "format": "date-time"
          }
        },
        "additionalProperties": false
      },
      "SupplierPaginatedResponse": {
        "type": "object",
        "properties": {
          "success": {
            "type": "boolean"
          },
          "message": {
            "type": "string",
            "nullable": true
          },
          "data": {
            "type": "array",
            "items": {
              "$ref": "#/components/schemas/Supplier"
            },
            "nullable": true
          },
          "totalRecords": {
            "type": "integer",
            "format": "int32"
          },
          "pageNumber": {
            "type": "integer",
            "format": "int32"
          },
          "pageSize": {
            "type": "integer",
            "format": "int32"
          },
          "totalPages": {
            "type": "integer",
            "format": "int32",
            "readOnly": true
          }
        },
        "additionalProperties": false
      },
      "SupplierUpdateDto": {
        "required": [
          "name"
        ],
        "type": "object",
        "properties": {
          "name": {
            "maxLength": 100,
            "minLength": 2,
            "type": "string"
          },
          "contact": {
            "maxLength": 15,
            "minLength": 0,
            "type": "string",
            "format": "tel",
            "nullable": true
          },
          "address": {
            "maxLength": 500,
            "minLength": 0,
            "type": "string",
            "nullable": true
          },
          "notes": {
            "maxLength": 1000,
            "minLength": 0,
            "type": "string",
            "nullable": true
          }
        },
        "additionalProperties": false
      },
      "UpdateUserDto": {
        "required": [
          "name",
          "role"
        ],
        "type": "object",
        "properties": {
          "name": {
            "maxLength": 100,
            "minLength": 2,
            "type": "string"
          },
          "email": {
            "maxLength": 100,
            "minLength": 0,
            "type": "string",
            "format": "email",
            "nullable": true
          },
          "phone": {
            "maxLength": 15,
            "minLength": 0,
            "type": "string",
            "format": "tel",
            "nullable": true
          },
          "address": {
            "maxLength": 500,
            "minLength": 0,
            "type": "string",
            "nullable": true
          },
          "role": {
            "minLength": 1,
            "pattern": "^(admin|manager|staff)$",
            "type": "string"
          },
          "notes": {
            "maxLength": 1000,
            "minLength": 0,
            "type": "string",
            "nullable": true
          }
        },
        "additionalProperties": false
      },
      "UpdateUserStatusDto": {
        "required": [
          "isActive"
        ],
        "type": "object",
        "properties": {
          "isActive": {
            "type": "boolean"
          }
        },
        "additionalProperties": false
      },
      "User": {
        "type": "object",
        "properties": {
          "staffId": {
            "type": "integer",
            "format": "int32"
          },
          "name": {
            "type": "string",
            "nullable": true
          },
          "email": {
            "type": "string",
            "nullable": true
          },
          "phone": {
            "type": "string",
            "nullable": true
          },
          "address": {
            "type": "string",
            "nullable": true
          },
          "username": {
            "type": "string",
            "nullable": true
          },
          "passwordHash": {
            "type": "string",
            "nullable": true
          },
          "role": {
            "type": "string",
            "nullable": true
          },
          "isActive": {
            "type": "boolean"
          },
          "createdAt": {
            "type": "string",
            "format": "date-time"
          },
          "updatedAt": {
            "type": "string",
            "format": "date-time"
          },
          "lastLogin": {
            "type": "string",
            "format": "date-time",
            "nullable": true
          },
          "notes": {
            "type": "string",
            "nullable": true
          }
        },
        "additionalProperties": false
      },
      "UserApiResponse": {
        "type": "object",
        "properties": {
          "success": {
            "type": "boolean"
          },
          "message": {
            "type": "string",
            "nullable": true
          },
          "data": {
            "$ref": "#/components/schemas/User"
          },
          "errors": {
            "type": "array",
            "items": {
              "type": "string"
            },
            "nullable": true
          },
          "timestamp": {
            "type": "string",
            "format": "date-time"
          }
        },
        "additionalProperties": false
      },
      "UserListApiResponse": {
        "type": "object",
        "properties": {
          "success": {
            "type": "boolean"
          },
          "message": {
            "type": "string",
            "nullable": true
          },
          "data": {
            "type": "array",
            "items": {
              "$ref": "#/components/schemas/User"
            },
            "nullable": true
          },
          "errors": {
            "type": "array",
            "items": {
              "type": "string"
            },
            "nullable": true
          },
          "timestamp": {
            "type": "string",
            "format": "date-time"
          }
        },
        "additionalProperties": false
      },
      "UserLoginResponse": {
        "type": "object",
        "properties": {
          "staffId": {
            "type": "integer",
            "format": "int32"
          },
          "name": {
            "type": "string",
            "nullable": true
          },
          "username": {
            "type": "string",
            "nullable": true
          },
          "role": {
            "type": "string",
            "nullable": true
          },
          "token": {
            "type": "string",
            "nullable": true
          },
          "expiresAt": {
            "type": "string",
            "format": "date-time"
          }
        },
        "additionalProperties": false
      },
      "UserLoginResponseApiResponse": {
        "type": "object",
        "properties": {
          "success": {
            "type": "boolean"
          },
          "message": {
            "type": "string",
            "nullable": true
          },
          "data": {
            "$ref": "#/components/schemas/UserLoginResponse"
          },
          "errors": {
            "type": "array",
            "items": {
              "type": "string"
            },
            "nullable": true
          },
          "timestamp": {
            "type": "string",
            "format": "date-time"
          }
        },
        "additionalProperties": false
      },
      "UserPaginatedResponse": {
        "type": "object",
        "properties": {
          "success": {
            "type": "boolean"
          },
          "message": {
            "type": "string",
            "nullable": true
          },
          "data": {
            "type": "array",
            "items": {
              "$ref": "#/components/schemas/User"
            },
            "nullable": true
          },
          "totalRecords": {
            "type": "integer",
            "format": "int32"
          },
          "pageNumber": {
            "type": "integer",
            "format": "int32"
          },
          "pageSize": {
            "type": "integer",
            "format": "int32"
          },
          "totalPages": {
            "type": "integer",
            "format": "int32",
            "readOnly": true
          }
        },
        "additionalProperties": false
      }
    }
  },
  "tags": [
    {
      "name": "Customers"
    },
    {
      "name": "Suppliers"
    },
    {
      "name": "Users"
    }
  ]
}